taskman_cli/__init__.py
taskman_cli/helper_functions.py
taskman_cli/main.py
taskman_cli-1.0.0.dist-info/licenses/LICENSE
taskman_cli-1.0.0.dist-info/METADATA
taskman_cli-1.0.0.dist-info/WHEEL
taskman_cli-1.0.0.dist-info/entry_points.txt
taskman_cli-1.0.0.dist-info/top_level.txt
taskman_cli-1.0.0.dist-info/RECORD
