Metadata-Version: 2.4
Name: taskman-cli
Version: 1.0.0
Summary: A minimalistic and user-friendly task management application built with Python
Author-email: Taha Yasser Adnan <taha.y.adnan@gmail.com>
Project-URL: Homepage, https://github.com/tahadnan/TaskMan-CLI-PyPI
Project-URL: Bug Tracker, https://github.com/tahadnan/TaskMan-CLI-PyPI/issues
Classifier: Programming Language :: Python :: 3
Classifier: License :: OSI Approved :: MIT License
Classifier: Operating System :: OS Independent
Classifier: Development Status :: 7 - Inactive
Requires-Python: >=3.6
License-File: LICENSE
Requires-Dist: prompt_toolkit
Requires-Dist: pygments
Requires-Dist: ttask-manager
Requires-Dist: platformdirs
Dynamic: license-file
